package_name/__init__.py
newsrec-0.0.1.dist-info/METADATA
newsrec-0.0.1.dist-info/WHEEL
newsrec-0.0.1.dist-info/top_level.txt
newsrec-0.0.1.dist-info/RECORD
