Metadata-Version: 2.1
Name: newsrec
Version: 0.0.1
Home-page: 
Author: Johannes Kruse
Author-email: johannes-kruse@hotmail.com
License: MIT
Keywords: Recommender Systems
Requires-Dist: numpy
Requires-Dist: spicy
Requires-Dist: pytest
